setup.py
wjmLab/__init__.py
wjmLab/wjmLab.py
wjmLab.egg-info/PKG-INFO
wjmLab.egg-info/SOURCES.txt
wjmLab.egg-info/dependency_links.txt
wjmLab.egg-info/requires.txt
wjmLab.egg-info/top_level.txt