Metadata-Version: 1.0
Name: wjmLab
Version: 0.0.1
Summary: isoweek calculation and so on
Home-page: UNKNOWN
Author: JELLYPOWER
Author-email: JELLYPOWER@naver.com
License: MIT
Keywords: calendar,isoweek,listsum
Platform: UNKNOWN
